spivolt/__init__.py
spivolt/spivolt.py
spivolt/api/__init__.py
spivolt/api/base.py
spivolt/data/__init__.py
spivolt/data/accessors.py
spivolt/parameters/__init__.py
spivolt/parameters/dates.py
spivolt-0.0.3.dist-info/LICENSE
spivolt-0.0.3.dist-info/METADATA
spivolt-0.0.3.dist-info/WHEEL
spivolt-0.0.3.dist-info/top_level.txt
spivolt-0.0.3.dist-info/RECORD
