Metadata-Version: 2.1
Name: spivolt
Version: 0.0.3
Summary: A wrapper for the SPiVolt API.
Home-page: https://github.com/brythonick/spivolt
Author: Nick Farnham
Author-email: nick.farnham@southwales.ac.uk
License: UNKNOWN
Platform: UNKNOWN
Classifier: Programming Language :: Python :: 3.6
Classifier: License :: OSI Approved :: GNU General Public License v3 (GPLv3)
Classifier: Operating System :: OS Independent
Classifier: Development Status :: 2 - Pre-Alpha
Classifier: Topic :: Scientific/Engineering
Requires-Python: >=3.6
Requires-Dist: pandas
Requires-Dist: requests
Requires-Dist: numpy (>=1.1.5)
Requires-Dist: matplotlib
